Workbook

Sheet Análisis STRIDE
A1: Taller 5 – STRIDE (Cliente real) | KOOLT
A2: Flujo crítico analizado: pedido + pago + preparación + entrega
A4: ID | B4: Componente / Activo | C4: Tipo STRIDE | D4: Descripción de la amenaza | E4: Escenario de ataque | F4: Impacto | G4: Probabilidad | H4: Nivel de riesgo | I4: Controles de seguridad existentes | J4: Mitigación recomendada | K4: Responsable | L4: Estado
A5: K1 | B5: Kiosco/Tablet de Pedido | C5: Manipulación | D5: Alteración del pedido antes de enviarlo al backend, afectando precios, extras o cantidades. | E5: Se modifican parámetros del frontend o requests desde el dispositivo para enviar un pedido inconsistente. | F5: 4 | G5: 3 | H5: =F5*G5 | I5: Validación del lado servidor de precios y reglas, firmado de payloads, límites de parámetros permitidos. | J5: Revalidar totalmente en backend, bloquear campos sensibles en cliente y registrar discrepancias de precios. | K5: Andrés Ricaurte | L5: Pendiente
A6: K2 | B6: Terminal POS | C6: Suplantación | D6: Uso de un POS no autorizado o de una sesión de caja comprometida para registrar pedidos falsos. | E6: Dispositivo no enrolado o credenciales de caja compartidas permiten operar como terminal legítima. | F6: 5 | G6: 3 | H6: =F6*G6 | I6: Autenticación del dispositivo, cuentas individuales, mTLS entre POS y backend. | J6: Enrolamiento formal de terminales, MFA para operaciones administrativas y rotación periódica de credenciales. | K6: Juan Restrepo | L6: En análisis
A7: K3 | B7: Red Local / Router | C7: Denegación de servicio | D7: Interrupción del servicio en tienda por falla del router o congestión de la red interna. | E7: El router único falla o el Wi‑Fi se satura durante horas pico, afectando POS, KDS e impresión. | F7: 4 | G7: 4 | H7: =F7*G7 | I7: QoS básico, segmentación de red, monitoreo de conectividad, equipos de respaldo limitados. | J7: Redundancia de enlace, 4G failover, red separada para invitados y monitoreo de ancho de banda. | K7: Juan Jaime | L7: Pendiente
A8: K4 | B8: Servicio de Inventario | C8: Divulgación de información | D8: Exposición de datos operativos como stock, costos o reglas internas de reposición. | E8: Endpoints o reportes sin control por rol revelan información sensible a usuarios no autorizados. | F8: 3 | G8: 3 | H8: =F8*G8 | I8: RBAC, segmentación por tienda, auditoría de consultas y ocultamiento de campos sensibles. | J8: Revisar permisos por perfil, limitar exportaciones y separar vistas operativas de vistas administrativas. | K8: Andrés Ricaurte | L8: En progreso
A9: K5 | B9: Integración Inventario ↔ POS | C9: Manipulación | D9: Alteración de respuestas de disponibilidad para forzar pedidos con insumos inexistentes o negar ventas válidas. | E9: Mensajes sin validación de integridad pueden ser interceptados o alterados en tránsito. | F9: 4 | G9: 2 | H9: =F9*G9 | I9: TLS, control de integridad de mensajes, reintentos controlados y bitácora de sincronización. | J9: Firmar mensajes, correlacionar respuestas con solicitudes y agregar verificación cruzada en backend. | K9: Juan Restrepo | L9: Pendiente
A10: K6 | B10: Pasarela de Pago | C10: Repudio | D10: Disputa del cobro o pérdida de trazabilidad entre autorización, cobro y comprobante. | E10: No se conserva correlación entre id de transacción, pedido y recibo emitido. | F10: 4 | G10: 3 | H10: =F10*G10 | I10: Identificador único de transacción, conciliación diaria y registro del resultado del cobro. | J10: Trazabilidad end-to-end de pago, hash del comprobante y conciliación automática con caja. | K10: Juan Jaime | L10: En análisis
A11: K7 | B11: Proceso de Pago | C11: Divulgación de información | D11: Fuga de datos sensibles de pago o tokens a través de logs, pantallas o configuraciones inseguras. | E11: Se exponen fragmentos de datos de pago en bitácoras, consolas o pantallas compartidas. | F11: 5 | G11: 2 | H11: =F11*G11 | I11: Tokenización, políticas de enmascaramiento, restricción de logs y acceso controlado a consola. | J11: No registrar datos sensibles, revisar masking extremo a extremo y endurecer permisos de observabilidad. | K11: Andrés Ricaurte | L11: Pendiente
A12: K8 | B12: Backend de Pedidos | C12: Denegación de servicio | D12: Saturación del backend en horas pico, con pedidos lentos o pérdida de confirmaciones. | E12: Promociones, picos de demanda o múltiples reintentos de clientes afectan el throughput del servicio. | F12: 4 | G12: 3 | H12: =F12*G12 | I12: Autoescalado, colas internas, límites por cliente y monitoreo de latencia. | J12: Pruebas de carga, caché de catálogos, cola de preparación desacoplada y umbrales de escalado más agresivos. | K12: Juan Restrepo | L12: En progreso
A13: K9 | B13: Pantalla de Cocina (KDS) | C13: Suplantación | D13: Órdenes falsas o alteradas aparecen en cocina por acceso no autorizado al KDS. | E13: Una terminal no autorizada se conecta o una sesión abierta permite manipular estados del pedido. | F13: 3 | G13: 3 | H13: =F13*G13 | I13: Autenticación por rol, cuentas individuales y bloqueo automático por inactividad. | J13: Enrolar dispositivos, exigir reautenticación para cambios críticos y limitar funciones por perfil. | K13: Juan Jaime | L13: Pendiente
A14: K10 | B14: Base de Datos de Pedidos | C14: Manipulación | D14: Modificación no autorizada de pedidos, pagos o estados después del cierre de caja. | E14: Acceso excesivo a BD o scripts sin control alteran registros históricos. | F14: 5 | G14: 2 | H14: =F14*G14 | I14: Permisos mínimos, auditoría de cambios, respaldos y segregación de funciones. | J14: Inmutabilidad lógica de pedidos cerrados, revisiones de acceso y alertas por cambios fuera de horario. | K14: Andrés Ricaurte | L14: En análisis
A15: K11 | B15: Panel de Precios y Promociones | C15: Elevación de privilegios | D15: Un empleado obtiene permisos para cambiar precios, descuentos o promociones sin autorización. | E15: Permisos excesivos, cuentas compartidas o validaciones débiles permiten elevar privilegios. | F15: 5 | G15: 3 | H15: =F15*G15 | I15: RBAC, revisión de permisos, aprobación para cambios de precio y trazabilidad de edición. | J15: Doble aprobación para cambios comerciales, MFA para administradores y revisión mensual de accesos. | K15: Juan Restrepo | L15: Pendiente
A16: K12 | B16: Entrega del Producto / Caja | C16: Repudio | D16: El cliente reclama que no recibió el producto correcto o que nunca se le entregó. | E16: No existe evidencia suficiente del estado final del pedido ni del momento de entrega. | F16: 3 | G16: 3 | H16: =F16*G16 | I16: Marcado de estado entregado, impresión de ticket y referencia del pedido en caja. | J16: Confirmación de entrega en POS, correlación con ticket y procedimiento de reclamos con trazabilidad. | K16: Juan Jaime | L16: En progreso
A18: Escala sugerida
A19: Impacto / Probabilidad: 1 = Muy bajo, 2 = Bajo, 3 = Medio, 4 = Alto, 5 = Muy alto
A20: Nivel de riesgo = Impacto × Probabilidad
A21: Semáforo orientativo: 1–5 Bajo, 6–12 Medio, 13–25 Alto

Sheet Resumen
A1: Resumen Ejecutivo
A2: Flujo crítico analizado: pedido + pago + preparación + entrega
A4: Total de amenazas | B4: =COUNTA('Análisis STRIDE'!A5:A16) | D4: Amenaza con mayor riesgo | E4: =INDEX('Análisis STRIDE'!D5:D16,MATCH(MAX('Análisis STRIDE'!H5:H16),'Análisis STRIDE'!H5:H16,0))
A5: Riesgo alto (>=13) | B5: =COUNTIF('Análisis STRIDE'!H5:H16,">=13") | D5: Componente crítico | E5: =INDEX('Análisis STRIDE'!B5:B16,MATCH(MAX('Análisis STRIDE'!H5:H16),'Análisis STRIDE'!H5:H16,0))
A6: Riesgo medio (6-12) | B6: =COUNTIFS('Análisis STRIDE'!H5:H16,">=6",'Análisis STRIDE'!H5:H16,"<=12") | D6: Promedio de riesgo | E6: =ROUND(AVERAGE('Análisis STRIDE'!H5:H16),1)
A7: Riesgo bajo (1-5) | B7: =COUNTIFS('Análisis STRIDE'!H5:H16,">=1",'Análisis STRIDE'!H5:H16,"<=5") | D7: Estado más frecuente
A9: Responsable | B9: Cantidad | D9: Estado | E9: Cantidad
A10: Andrés Ricaurte | B10: =COUNTIF('Análisis STRIDE'!K5:K16,A10) | D10: Pendiente | E10: =COUNTIF('Análisis STRIDE'!L5:L16,D10)
A11: Juan Restrepo | B11: =COUNTIF('Análisis STRIDE'!K5:K16,A11) | D11: En análisis | E11: =COUNTIF('Análisis STRIDE'!L5:L16,D11)
A12: Juan Jaime | B12: =COUNTIF('Análisis STRIDE'!K5:K16,A12) | D12: En progreso | E12: =COUNTIF('Análisis STRIDE'!L5:L16,D12)
D13: Mitigado | E13: =COUNTIF('Análisis STRIDE'!L5:L16,D13)
A15: Integrantes encargados
A16: - Andrés Ricaurte
A17: - Juan Restrepo
A18: - Juan Jaime
